paddle_serving_server/__init__.py
paddle_serving_server/benchmark_utils.py
paddle_serving_server/dag.py
paddle_serving_server/env.py
paddle_serving_server/monitor.py
paddle_serving_server/parse_profile.py
paddle_serving_server/serve.py
paddle_serving_server/server.py
paddle_serving_server/util.py
paddle_serving_server/version.py
paddle_serving_server/web_service.py
paddle_serving_server/env_check/run.py
paddle_serving_server/env_check/test_fit_a_line.py
paddle_serving_server/env_check/test_uci_pipeline.py
paddle_serving_server/env_check/util.py
paddle_serving_server/env_check/fit_a_line/uci_housing_client/serving_client_conf.prototxt
paddle_serving_server/env_check/fit_a_line/uci_housing_client/serving_client_conf.stream.prototxt
paddle_serving_server/env_check/fit_a_line/uci_housing_model/__model__
paddle_serving_server/env_check/fit_a_line/uci_housing_model/fc_0.b_0
paddle_serving_server/env_check/fit_a_line/uci_housing_model/fc_0.w_0
paddle_serving_server/env_check/fit_a_line/uci_housing_model/fluid_time_file
paddle_serving_server/env_check/fit_a_line/uci_housing_model/serving_server_conf.prototxt
paddle_serving_server/env_check/fit_a_line/uci_housing_model/serving_server_conf.stream.prototxt
paddle_serving_server/env_check/simple_web_service/config_cpu.yml
paddle_serving_server/env_check/simple_web_service/config_gpu.yml
paddle_serving_server/env_check/simple_web_service/web_service.py
paddle_serving_server/env_check/simple_web_service/uci_housing_client/serving_client_conf.prototxt
paddle_serving_server/env_check/simple_web_service/uci_housing_client/serving_client_conf.stream.prototxt
paddle_serving_server/env_check/simple_web_service/uci_housing_model/__model__
paddle_serving_server/env_check/simple_web_service/uci_housing_model/fc_0.b_0
paddle_serving_server/env_check/simple_web_service/uci_housing_model/fc_0.w_0
paddle_serving_server/env_check/simple_web_service/uci_housing_model/serving_server_conf.prototxt
paddle_serving_server-0.9.0.dist-info/METADATA
paddle_serving_server-0.9.0.dist-info/WHEEL
paddle_serving_server-0.9.0.dist-info/top_level.txt
paddle_serving_server-0.9.0.dist-info/RECORD
